pgnhelper/__init__.py
pgnhelper/__main__.py
pgnhelper/app.py
pgnhelper/eco.py
pgnhelper/elo.py
pgnhelper/record.py
pgnhelper/roundrobin.py
pgnhelper/sort.py
pgnhelper/swiss.py
pgnhelper/tiebreak.py
pgnhelper/utility.py
pgnhelper-0.10.2.dist-info/LICENSE
pgnhelper-0.10.2.dist-info/METADATA
pgnhelper-0.10.2.dist-info/WHEEL
pgnhelper-0.10.2.dist-info/entry_points.txt
pgnhelper-0.10.2.dist-info/top_level.txt
pgnhelper-0.10.2.dist-info/RECORD
